[
    {
        "id": 17857788685948670,
        "created_at": 1589625911,
        "text": "38 mm id\u00e9al pour une femme sportive et raffin\u00e9e, et l\u2019or rose , couleur d\u00e9licate qui se fond sur la peau .\nLa couleur de la discr\u00e8te \u00e9l\u00e9gance !\u2764\ufe0f",
        "owner": {
            "id": "13202569198",
            "is_verified": false,
            "profile_pic_url": "https://scontent-zrh1-1.cdninstagram.com/v/t51.2885-19/s150x150/56960791_1075960875940594_1121880440223825920_n.jpg?_nc_ht=scontent-zrh1-1.cdninstagram.com&_nc_ohc=6BsiegUHyjwAX_k3d7K&oh=06ae306e5a22ceeb36f815676e422a11&oe=5EEB34A2",
            "username": "nadegekaminski"
        },
        "likes_count": 0,
        "answers": []
    },
    {
        "id": 17869880236741746,
        "created_at": 1589525117,
        "text": "\u2764\ufe0f",
        "owner": {
            "id": "34590007489",
            "is_verified": false,
            "profile_pic_url": "https://scontent-zrh1-1.cdninstagram.com/v/t51.2885-19/s150x150/95206613_547038519542851_3973745966082686976_n.jpg?_nc_ht=scontent-zrh1-1.cdninstagram.com&_nc_ohc=d0chwi0AbkUAX-e5wVC&oh=1b579d99a896e07b97c03abd0a2f3d32&oe=5EE9BB0B",
            "username": "wristactionuk"
        },
        "likes_count": 0,
        "answers": []
    },
    {
        "id": 17878865416622339,
        "created_at": 1589517131,
        "text": "Gougers time pieces",
        "owner": {
            "id": "25726820488",
            "is_verified": false,
            "profile_pic_url": "https://scontent-zrh1-1.cdninstagram.com/v/t51.2885-19/s150x150/75048661_408746233344122_1111815987524534272_n.jpg?_nc_ht=scontent-zrh1-1.cdninstagram.com&_nc_ohc=RV8eC6iz8igAX97QoRU&oh=a3285bf02e37e431dcce57cb0deb68ae&oe=5EEA933B",
            "username": "montoyawatchservicescenter"
        },
        "likes_count": 0,
        "answers": []
    },
    {
        "id": 17846881187121462,
        "created_at": 1589479234,
        "text": "\u0645\u0639\u0634\u0648\u0642\u062a\u064a",
        "owner": {
            "id": "309966771",
            "is_verified": false,
            "profile_pic_url": "https://scontent-zrh1-1.cdninstagram.com/v/t51.2885-19/s150x150/19761860_667905803402959_6478596869072093184_a.jpg?_nc_ht=scontent-zrh1-1.cdninstagram.com&_nc_ohc=9IZdZBa0bSQAX9n9ef1&oh=4fc987cd9a0884b6fdff62b2b825a812&oe=5EEAAC4D",
            "username": "ashraf_eltamimi"
        },
        "likes_count": 0,
        "answers": []
    },
    {
        "id": 17903088745461931,
        "created_at": 1589478701,
        "text": "\ud83d\udd25\ud83d\udd25\ud83d\udd25\ud83d\udd25\ud83d\udd25\ud83d\udd25\ud83d\udd25",
        "owner": {
            "id": "2119452645",
            "is_verified": false,
            "profile_pic_url": "https://scontent-zrh1-1.cdninstagram.com/v/t51.2885-19/s150x150/93947726_2672723236295051_3670546834335465472_n.jpg?_nc_ht=scontent-zrh1-1.cdninstagram.com&_nc_ohc=G8IsCvZKib4AX_ixY3Z&oh=824a23996d9375296e425e36af4310c2&oe=5EEA295C",
            "username": "luxurymachines"
        },
        "likes_count": 0,
        "answers": []
    },
    {
        "id": 17896921174493203,
        "created_at": 1589478549,
        "text": "Amazing details \u2728",
        "owner": {
            "id": "189467406",
            "is_verified": false,
            "profile_pic_url": "https://scontent-zrh1-1.cdninstagram.com/v/t51.2885-19/s150x150/91137572_253852818966317_8010588111299936256_n.jpg?_nc_ht=scontent-zrh1-1.cdninstagram.com&_nc_ohc=onBxUaVSPpcAX9p967S&oh=643f6578afc017a05e3029138d85f36a&oe=5EE7A07B",
            "username": "michelleaarlaht"
        },
        "likes_count": 0,
        "answers": []
    },
    {
        "id": 17855520895962839,
        "created_at": 1589474231,
        "text": "Best best",
        "owner": {
            "id": "34962380279",
            "is_verified": false,
            "profile_pic_url": "https://scontent-zrh1-1.cdninstagram.com/v/t51.2885-19/s150x150/96939462_2603167526563150_1647112076751011840_n.jpg?_nc_ht=scontent-zrh1-1.cdninstagram.com&_nc_ohc=DtxKMKyKIYgAX9eb_4x&oh=eb115d93487a996c57d7b84adf7fda17&oe=5EE9CCF6",
            "username": "honey_taney_kiss"
        },
        "likes_count": 0,
        "answers": []
    },
    {
        "id": 17879086831621778,
        "created_at": 1589468011,
        "text": "@_girlwithnojob___ buy for me \ud83e\udd7a\ud83e\udd7a\ud83e\udd70",
        "owner": {
            "id": "6016561996",
            "is_verified": false,
            "profile_pic_url": "https://scontent-zrh1-1.cdninstagram.com/v/t51.2885-19/s150x150/58430452_417636575735807_2094101168765534208_n.jpg?_nc_ht=scontent-zrh1-1.cdninstagram.com&_nc_ohc=4KQCmqR8rgEAX8N-lHw&oh=06218c4307997ba13b68b9d0d6e3ff17&oe=5EE9D955",
            "username": "tan_ya.28"
        },
        "likes_count": 0,
        "answers": [
            {
                "id": 17872998541700515,
                "created_at": 1589468179,
                "text": "@_girlwithnojob___ I'll bring out the Learjet for now. Just gotta make a quick trip to the Maldives to pick up my Belgian lipstick in my Italian house",
                "owner": {
                    "id": "6016561996",
                    "is_verified": false,
                    "profile_pic_url": "https://scontent-zrh1-1.cdninstagram.com/v/t51.2885-19/s150x150/58430452_417636575735807_2094101168765534208_n.jpg?_nc_ht=scontent-zrh1-1.cdninstagram.com&_nc_ohc=4KQCmqR8rgEAX8N-lHw&oh=06218c4307997ba13b68b9d0d6e3ff17&oe=5EE9D955",
                    "username": "tan_ya.28"
                },
                "likes_count": 1
            },
            {
                "id": 17924409868385891,
                "created_at": 1589468090,
                "text": "@tan_ya.28 of courseeeee. They\u2019ll be delivered to my German house in Switzerland so we can just fly the A380 to Switzerland and get it",
                "owner": {
                    "id": "1610384439",
                    "is_verified": false,
                    "profile_pic_url": "https://scontent-zrh1-1.cdninstagram.com/v/t51.2885-19/s150x150/69444293_2442803845955303_2145457875135234048_n.jpg?_nc_ht=scontent-zrh1-1.cdninstagram.com&_nc_ohc=FhactFjqNgIAX_sU0mk&oh=ffc6f71e57ce8f9d87acab3eb9142fa8&oe=5EEA7FA2",
                    "username": "_girlwithnojob___"
                },
                "likes_count": 1
            }
        ]
    },
    {
        "id": 17867828185774749,
        "created_at": 1589458692,
        "text": "\u2764\ufe0f\u2764\ufe0f\u2764\ufe0f\u2764\ufe0f\ud83d\ude0d\ud83d\ude0d\ud83d\ude0d\ud83d\ude0d",
        "owner": {
            "id": "19008934052",
            "is_verified": false,
            "profile_pic_url": "https://scontent-zrh1-1.cdninstagram.com/v/t51.2885-19/s150x150/67451986_1441701069300991_1448190065141350400_n.jpg?_nc_ht=scontent-zrh1-1.cdninstagram.com&_nc_ohc=2aGi-0r9U90AX8WT2tr&oh=89cc8b54bbe8c6516a64876b566599b2&oe=5EEA729B",
            "username": "octaviocucaquinones"
        },
        "likes_count": 0,
        "answers": []
    },
    {
        "id": 18106234228142651,
        "created_at": 1589445781,
        "text": "\ud83d\ude0d\ud83d\ude0d\ud83d\ude0d\ud83d\ude0d\ud83d\ude0d\ud83d\ude0d",
        "owner": {
            "id": "4497932905",
            "is_verified": false,
            "profile_pic_url": "https://scontent-zrh1-1.cdninstagram.com/v/t51.2885-19/s150x150/75349302_2529085460656097_1048042603716542464_n.jpg?_nc_ht=scontent-zrh1-1.cdninstagram.com&_nc_ohc=sS8b8sNW5_0AX_StVt9&oh=5ef4a1cfb783ca3f4d0328b552a37072&oe=5EE94DEF",
            "username": "anpro79"
        },
        "likes_count": 0,
        "answers": []
    },
    {
        "id": 17848827806086955,
        "created_at": 1589434680,
        "text": "@cadillacx7",
        "owner": {
            "id": "2042289011",
            "is_verified": false,
            "profile_pic_url": "https://scontent-zrh1-1.cdninstagram.com/v/t51.2885-19/s150x150/11312423_1631197593831979_895451272_a.jpg?_nc_ht=scontent-zrh1-1.cdninstagram.com&_nc_ohc=beKN2vGP01kAX859Uzb&oh=9918763d30308269e3fb7a40e7a3723f&oe=5EE823E7",
            "username": "jorgethemuppet"
        },
        "likes_count": 0,
        "answers": []
    },
    {
        "id": 17862420733875588,
        "created_at": 1589427963,
        "text": "@danif_877",
        "owner": {
            "id": "1702305608",
            "is_verified": false,
            "profile_pic_url": "https://scontent-zrh1-1.cdninstagram.com/v/t51.2885-19/s150x150/20766875_266712480492892_1645993010137137152_a.jpg?_nc_ht=scontent-zrh1-1.cdninstagram.com&_nc_ohc=vwe_3ARI4sAAX8Rtvva&oh=31f6401de1153c6775fb675702ef6793&oe=5EE7725C",
            "username": "jaimirokuai"
        },
        "likes_count": 0,
        "answers": [
            {
                "id": 17873689699691114,
                "created_at": 1589429094,
                "text": "@jaimirokuai ada mieda",
                "owner": {
                    "id": "2907182379",
                    "is_verified": false,
                    "profile_pic_url": "https://scontent-zrh1-1.cdninstagram.com/v/t51.2885-19/s150x150/12552471_1694428407493327_522500507_a.jpg?_nc_ht=scontent-zrh1-1.cdninstagram.com&_nc_ohc=lo8_2TPdJPkAX_NZdL8&oh=1acc1e4afae5d76da9a58077aca8ef13&oe=5EE96492",
                    "username": "danif_877"
                },
                "likes_count": 0
            }
        ]
    },
    {
        "id": 18144367183042567,
        "created_at": 1589407771,
        "text": "@waleedziw",
        "owner": {
            "id": "199179919",
            "is_verified": false,
            "profile_pic_url": "https://scontent-zrh1-1.cdninstagram.com/v/t51.2885-19/s150x150/79590870_2628849487211297_8967055045828804608_n.jpg?_nc_ht=scontent-zrh1-1.cdninstagram.com&_nc_ohc=jtPPAIAvZZUAX-iCLah&oh=74781ba34815a59f20677b6c48314af9&oe=5EE952A6",
            "username": "devonltravels"
        },
        "likes_count": 0,
        "answers": []
    },
    {
        "id": 17854994986967124,
        "created_at": 1589406426,
        "text": "Perfection qualit\u00e9 \ud83d\udc4c",
        "owner": {
            "id": "8784252329",
            "is_verified": false,
            "profile_pic_url": "https://scontent-zrh1-1.cdninstagram.com/v/t51.2885-19/s150x150/96420063_670984530387815_6062826932259520512_n.jpg?_nc_ht=scontent-zrh1-1.cdninstagram.com&_nc_ohc=nT_WOdR6X8cAX9x5ddu&oh=14ec22f01785a0fb21f8830846614ff0&oe=5EEB4EE4",
            "username": "hadjbams"
        },
        "likes_count": 0,
        "answers": []
    },
    {
        "id": 17872886905701150,
        "created_at": 1589405544,
        "text": "Amazing watch",
        "owner": {
            "id": "30354831291",
            "is_verified": false,
            "profile_pic_url": "https://scontent-zrh1-1.cdninstagram.com/v/t51.2885-19/s150x150/85104382_621754808613398_7484746683905998848_n.jpg?_nc_ht=scontent-zrh1-1.cdninstagram.com&_nc_ohc=BwY4xcrn7rUAX9KH9Sl&oh=3773356d83a4442135c310334b9bf934&oe=5EE951C6",
            "username": "watch_finder_2020"
        },
        "likes_count": 0,
        "answers": []
    },
    {
        "id": 17865364081791475,
        "created_at": 1589405078,
        "text": ".\n\ud83d\udcf7\n.\n#photography \n#ali_m.ph\n#edits\n#\ud83e\udd81",
        "owner": {
            "id": "26450646978",
            "is_verified": false,
            "profile_pic_url": "https://scontent-zrh1-1.cdninstagram.com/v/t51.2885-19/s150x150/96821272_2640877159489640_7709204737106640896_n.jpg?_nc_ht=scontent-zrh1-1.cdninstagram.com&_nc_ohc=ypAT917YOEoAX8Bhs-P&oh=c7f300f4f1a79261cd5aa6645a870bbf&oe=5EE7B544",
            "username": "ali_m.ph"
        },
        "likes_count": 0,
        "answers": []
    },
    {
        "id": 17941491769358937,
        "created_at": 1589405077,
        "text": ".\n\ud83d\udcf7\n.\n#photography \n#ali_m.ph\n#edits\n#\ud83e\udd81",
        "owner": {
            "id": "26450646978",
            "is_verified": false,
            "profile_pic_url": "https://scontent-zrh1-1.cdninstagram.com/v/t51.2885-19/s150x150/96821272_2640877159489640_7709204737106640896_n.jpg?_nc_ht=scontent-zrh1-1.cdninstagram.com&_nc_ohc=ypAT917YOEoAX8Bhs-P&oh=c7f300f4f1a79261cd5aa6645a870bbf&oe=5EE7B544",
            "username": "ali_m.ph"
        },
        "likes_count": 0,
        "answers": []
    },
    {
        "id": 17882121922603298,
        "created_at": 1589403673,
        "text": "Very pretty\ud83d\ude0d\u2764\ufe0f",
        "owner": {
            "id": "211867274",
            "is_verified": false,
            "profile_pic_url": "https://scontent-zrh1-1.cdninstagram.com/v/t51.2885-19/s150x150/12545484_589760061172106_433095734_a.jpg?_nc_ht=scontent-zrh1-1.cdninstagram.com&_nc_ohc=Mo6pGNjCmRQAX81Vwfj&oh=b5b7f780a90bf7d80ff0ac7af6c7dca8&oe=5EE907FB",
            "username": "exquisitetimepieces"
        },
        "likes_count": 0,
        "answers": []
    },
    {
        "id": 17849343980061871,
        "created_at": 1589402843,
        "text": "\u231a",
        "owner": {
            "id": "1914097917",
            "is_verified": false,
            "profile_pic_url": "https://scontent-zrh1-1.cdninstagram.com/v/t51.2885-19/s150x150/18723570_603659049988028_4631378718357454848_n.jpg?_nc_ht=scontent-zrh1-1.cdninstagram.com&_nc_ohc=qClr-KGDfSIAX9ga9fq&oh=dd71ae9bd3dc32590a20af89cee77db2&oe=5EEAC489",
            "username": "craftsman_ship"
        },
        "likes_count": 0,
        "answers": []
    },
    {
        "id": 17898671509471599,
        "created_at": 1589402746,
        "text": "HODINKEE - \"When Omega's designers sat down to discuss the very special 908th incarnation of the Speedmaster, the company said they deliberated for what seemed like an eternity on what it should look like. According to an inside source, in reality it was more like thirty minutes, but the conversation was indeed heated.  Ultimately it was decided that they would give horology fans what they always wanted: a concept piece entitled, 'The Watch Liberace Might Have Worn if he Were one of the Apollo 11 Astronauts.'\"",
        "owner": {
            "id": "6345733648",
            "is_verified": false,
            "profile_pic_url": "https://scontent-zrh1-1.cdninstagram.com/v/t51.2885-19/s150x150/95689206_661094404448069_5055316325757353984_n.jpg?_nc_ht=scontent-zrh1-1.cdninstagram.com&_nc_ohc=7OonjCfPnsMAX9VwviG&oh=0f9ff7b6276b163cd24ac894c2bff9d8&oe=5EE84E17",
            "username": "abitskiboo"
        },
        "likes_count": 0,
        "answers": []
    },
    {
        "id": 17917709971410984,
        "created_at": 1589402643,
        "text": "\ud83d\udc4f\ud83d\udc4f\ud83d\udc4f",
        "owner": {
            "id": "14449597709",
            "is_verified": false,
            "profile_pic_url": "https://scontent-zrh1-1.cdninstagram.com/v/t51.2885-19/s150x150/90713717_850005238834915_8199607264059850752_n.jpg?_nc_ht=scontent-zrh1-1.cdninstagram.com&_nc_ohc=37flguSCIroAX-veaFM&oh=73f43628cd738a39c5b2ee5373095bd6&oe=5EE8C71C",
            "username": "majid.beygi40"
        },
        "likes_count": 0,
        "answers": []
    },
    {
        "id": 17846834951119373,
        "created_at": 1589400873,
        "text": "I\u2019ve messaged omega through Instagram and had no response !",
        "owner": {
            "id": "1584775178",
            "is_verified": false,
            "profile_pic_url": "https://scontent-zrh1-1.cdninstagram.com/v/t51.2885-19/s150x150/66812251_659353861200971_6108048801832894464_n.jpg?_nc_ht=scontent-zrh1-1.cdninstagram.com&_nc_ohc=xM5VWc61UEYAX8Zeu1O&oh=b4ced3907d6e752d9d33e74850021c31&oe=5EE87E2C",
            "username": "jo.richmondx"
        },
        "likes_count": 0,
        "answers": []
    },
    {
        "id": 17951666809334079,
        "created_at": 1589400441,
        "text": "Love details! \u2764\ufe0f",
        "owner": {
            "id": "33462912083",
            "is_verified": false,
            "profile_pic_url": "https://scontent-zrh1-1.cdninstagram.com/v/t51.2885-19/s150x150/95832487_437711233761733_3366674917436162048_n.jpg?_nc_ht=scontent-zrh1-1.cdninstagram.com&_nc_ohc=Pqh7VzETng0AX_CX4_2&oh=98f0a90ec21c0afdb5508a58b58940fe&oe=5EE7B702",
            "username": "bwandstuff"
        },
        "likes_count": 0,
        "answers": []
    },
    {
        "id": 17882848933590919,
        "created_at": 1589399464,
        "text": "@carl.obena \ud83d\ude0a",
        "owner": {
            "id": "1564342921",
            "is_verified": false,
            "profile_pic_url": "https://scontent-zrh1-1.cdninstagram.com/v/t51.2885-19/s150x150/83021110_2597557493859822_1459889397141864448_n.jpg?_nc_ht=scontent-zrh1-1.cdninstagram.com&_nc_ohc=TaU1hdD45XkAX-57N3g&oh=84261ad61515a0cafce8c3c87f8e3482&oe=5EE7977F",
            "username": "jamesobena"
        },
        "likes_count": 0,
        "answers": []
    },
    {
        "id": 17893310206508896,
        "created_at": 1589398484,
        "text": "\ud83d\ude0d\ud83d\ude0d\ud83d\ude0d",
        "owner": {
            "id": "2226681725",
            "is_verified": false,
            "profile_pic_url": "https://scontent-zrh1-1.cdninstagram.com/v/t51.2885-19/s150x150/14624641_1318438141513921_5070505791132270592_a.jpg?_nc_ht=scontent-zrh1-1.cdninstagram.com&_nc_ohc=38qyy_5FnoMAX9CICu7&oh=fd446be856c5349017e4f0a6d6be402b&oe=5EEA0DE6",
            "username": "fiorellaamessina"
        },
        "likes_count": 0,
        "answers": []
    },
    {
        "id": 18144156049012185,
        "created_at": 1589397974,
        "text": "Not our fave Speedys but appreciate the details here for sure.",
        "owner": {
            "id": "16139327167",
            "is_verified": false,
            "profile_pic_url": "https://scontent-zrh1-1.cdninstagram.com/v/t51.2885-19/s150x150/96023913_237786233969666_181958050431631360_n.jpg?_nc_ht=scontent-zrh1-1.cdninstagram.com&_nc_ohc=bqn1ny7mdrIAX-QVEmB&oh=7215de26820bc7612d11f070ee0f6449&oe=5EE8792E",
            "username": "tennandtwomedia"
        },
        "likes_count": 1,
        "answers": []
    },
    {
        "id": 17857340320923692,
        "created_at": 1589397891,
        "text": "@shefyfishy Birthday coming soon.. #JustSaying",
        "owner": {
            "id": "209550228",
            "is_verified": false,
            "profile_pic_url": "https://scontent-zrh1-1.cdninstagram.com/v/t51.2885-19/15877150_1867678590179640_1896136797423927296_n.jpg?_nc_ht=scontent-zrh1-1.cdninstagram.com&_nc_ohc=g_BytVuwO9kAX9OwMlX&oh=99e10bc17b758ddc6cc07353d9e218d9&oe=5EEA9EBA",
            "username": "lucky3ash"
        },
        "likes_count": 0,
        "answers": [
            {
                "id": 17858577430909363,
                "created_at": 1589401740,
                "text": "@lucky3ash thank u for thinking of my birthday so much in advance baby \ud83d\ude18\ud83d\ude18\ud83e\udd23",
                "owner": {
                    "id": "198384392",
                    "is_verified": false,
                    "profile_pic_url": "https://scontent-zrh1-1.cdninstagram.com/v/t51.2885-19/s150x150/17586991_304078960010764_1545353164658573312_a.jpg?_nc_ht=scontent-zrh1-1.cdninstagram.com&_nc_ohc=5XocwsILaDMAX_hzzIA&oh=db38eb7bfa63eefbcfe1974c5edc18ce&oe=5EE7DF36",
                    "username": "shefyfishy"
                },
                "likes_count": 0
            }
        ]
    },
    {
        "id": 17845823219129349,
        "created_at": 1589397325,
        "text": "\u2764\ufe0f\u2764\ufe0f\u2764\ufe0f",
        "owner": {
            "id": "5972836168",
            "is_verified": false,
            "profile_pic_url": "https://scontent-zrh1-1.cdninstagram.com/v/t51.2885-19/s150x150/38487083_282148619067210_9020632177276092416_n.jpg?_nc_ht=scontent-zrh1-1.cdninstagram.com&_nc_ohc=AGWjH3qAt_cAX--4e_E&oh=3ae75d6d6c3b605611d304af49383d3e&oe=5EE93AE4",
            "username": "thedark_ea"
        },
        "likes_count": 0,
        "answers": []
    },
    {
        "id": 17871998038727919,
        "created_at": 1589397239,
        "text": "\u2728\u2728\u2728\u2728",
        "owner": {
            "id": "13195445",
            "is_verified": false,
            "profile_pic_url": "https://scontent-zrh1-1.cdninstagram.com/v/t51.2885-19/s150x150/41199482_1188526791304897_6237112345739395072_n.jpg?_nc_ht=scontent-zrh1-1.cdninstagram.com&_nc_ohc=GgfLsoyPAkIAX9JOwhF&oh=7ffff27594163a4d7ea5dc6eb2d51d4c&oe=5EE9A847",
            "username": "targetimpresa"
        },
        "likes_count": 0,
        "answers": []
    },
    {
        "id": 18141509758018682,
        "created_at": 1589397138,
        "text": "\ud83d\udc4d\ud83d\udc4d\ud83d\udc4d\ud83d\udc4d\ud83d\udc4c\ud83d\udc4c\ud83d\udc4c\ud83d\udc4c",
        "owner": {
            "id": "1961291892",
            "is_verified": false,
            "profile_pic_url": "https://scontent-zrh1-1.cdninstagram.com/v/t51.2885-19/s150x150/75300794_2747292535292955_3091341559275192320_n.jpg?_nc_ht=scontent-zrh1-1.cdninstagram.com&_nc_ohc=JLtrdILevfgAX_6JlT3&oh=b8bdf7f4d377074aa641e4ce262bab50&oe=5EE77EC0",
            "username": "hossein_sanezadeh"
        },
        "likes_count": 0,
        "answers": []
    },
    {
        "id": 18097903441156942,
        "created_at": 1589397132,
        "text": "\ud83c\udde8\ud83c\udded\ud83c\udde8\ud83c\udded\ud83c\udde8\ud83c\udded\ud83c\udde8\ud83c\udded",
        "owner": {
            "id": "1961291892",
            "is_verified": false,
            "profile_pic_url": "https://scontent-zrh1-1.cdninstagram.com/v/t51.2885-19/s150x150/75300794_2747292535292955_3091341559275192320_n.jpg?_nc_ht=scontent-zrh1-1.cdninstagram.com&_nc_ohc=JLtrdILevfgAX_6JlT3&oh=b8bdf7f4d377074aa641e4ce262bab50&oe=5EE77EC0",
            "username": "hossein_sanezadeh"
        },
        "likes_count": 0,
        "answers": []
    },
    {
        "id": 17876498356632287,
        "created_at": 1589397125,
        "text": "#omega watch \u231a",
        "owner": {
            "id": "1961291892",
            "is_verified": false,
            "profile_pic_url": "https://scontent-zrh1-1.cdninstagram.com/v/t51.2885-19/s150x150/75300794_2747292535292955_3091341559275192320_n.jpg?_nc_ht=scontent-zrh1-1.cdninstagram.com&_nc_ohc=JLtrdILevfgAX_6JlT3&oh=b8bdf7f4d377074aa641e4ce262bab50&oe=5EE77EC0",
            "username": "hossein_sanezadeh"
        },
        "likes_count": 0,
        "answers": []
    },
    {
        "id": 17876833336634504,
        "created_at": 1589396507,
        "text": "\u2600\ufe0f\u2600\ufe0f\u2600\ufe0f\u2600\ufe0f\ud83d\udd25\ud83d\udd25\ud83d\udd25",
        "owner": {
            "id": "3820517397",
            "is_verified": false,
            "profile_pic_url": "https://scontent-zrh1-1.cdninstagram.com/v/t51.2885-19/s150x150/90506295_578710282731375_1303895046784811008_n.jpg?_nc_ht=scontent-zrh1-1.cdninstagram.com&_nc_ohc=s6A7nuqvIAQAX83ozxX&oh=bd3735727b0092e595f250093368d66a&oe=5EE88B72",
            "username": "timeforticktack"
        },
        "likes_count": 0,
        "answers": []
    },
    {
        "id": 17854619227981309,
        "created_at": 1589396453,
        "text": "Wow this is amazing\u2764\ufe0f",
        "owner": {
            "id": "3255450495",
            "is_verified": false,
            "profile_pic_url": "https://scontent-zrh1-1.cdninstagram.com/v/t51.2885-19/s150x150/13267345_1084071028282446_1106642880_a.jpg?_nc_ht=scontent-zrh1-1.cdninstagram.com&_nc_ohc=SsVK2Etv-tAAX9ZCvL8&oh=483572864d0bdc972edcffd1fb46b233&oe=5EEA65C0",
            "username": "maytwentyswitzerland"
        },
        "likes_count": 0,
        "answers": []
    },
    {
        "id": 17866037236786704,
        "created_at": 1589394535,
        "text": "There is a penis on the top indice. .i.",
        "owner": {
            "id": "4872168661",
            "is_verified": false,
            "profile_pic_url": "https://scontent-sjc3-1.cdninstagram.com/v/t51.2885-19/44884218_345707102882519_2446069589734326272_n.jpg?_nc_ht=scontent-sjc3-1.cdninstagram.com&_nc_ohc=Jf9Z_lzbyhIAX9paiqa&oh=8b2771d04db3da2e0184ab1e2b522acd&oe=5EE82B0F&ig_cache_key=YW5vbnltb3VzX3Byb2ZpbGVfcGlj.2",
            "username": "tahvanainee"
        },
        "likes_count": 0,
        "answers": []
    },
    {
        "id": 18053790346234552,
        "created_at": 1589392653,
        "text": "Nice",
        "owner": {
            "id": "18252375051",
            "is_verified": false,
            "profile_pic_url": "https://scontent-zrh1-1.cdninstagram.com/v/t51.2885-19/s150x150/67712765_1267738723380764_1462779433390702592_n.jpg?_nc_ht=scontent-zrh1-1.cdninstagram.com&_nc_ohc=HOOqt_Rub2AAX9AA_zc&oh=2135f737dcab45a34772c281b4678b3f&oe=5EE79BA9",
            "username": "lady_in_time"
        },
        "likes_count": 0,
        "answers": []
    },
    {
        "id": 17857426783943790,
        "created_at": 1589391883,
        "text": "Pure perfection \ud83d\udc9b\ud83d\udc9b",
        "owner": {
            "id": "7611232580",
            "is_verified": false,
            "profile_pic_url": "https://scontent-zrh1-1.cdninstagram.com/v/t51.2885-19/s150x150/87228888_182584013038849_72401397580038144_n.jpg?_nc_ht=scontent-zrh1-1.cdninstagram.com&_nc_ohc=FzdZqYqcj4cAX_s13GU&oh=3e3fd3456dbb7539703c6b7ad4078203&oe=5EE882F4",
            "username": "wristtimeandwine"
        },
        "likes_count": 0,
        "answers": []
    },
    {
        "id": 17944306171351245,
        "created_at": 1589391450,
        "text": "My cup of Cappuccino \u2615",
        "owner": {
            "id": "35316332",
            "is_verified": false,
            "profile_pic_url": "https://scontent-zrh1-1.cdninstagram.com/v/t51.2885-19/s150x150/91316184_850769455423875_6371267856843145216_n.jpg?_nc_ht=scontent-zrh1-1.cdninstagram.com&_nc_ohc=NoGfNbHiq4MAX83hNhN&oh=aa2b6f29a7c252725744444f2fa88b45&oe=5EE86D5C",
            "username": "stephenlam1970"
        },
        "likes_count": 0,
        "answers": []
    },
    {
        "id": 18056359510224057,
        "created_at": 1589390401,
        "text": "\ud83d\udc95\ud83d\udc95\ud83d\udc95\ud83d\udc95",
        "owner": {
            "id": "1769910769",
            "is_verified": false,
            "profile_pic_url": "https://scontent-zrh1-1.cdninstagram.com/v/t51.2885-19/s150x150/72272926_2683824805017784_1133735537803264000_n.jpg?_nc_ht=scontent-zrh1-1.cdninstagram.com&_nc_ohc=3EKfSGMksyEAX90ozza&oh=4eaf1fd48b9a967dfa119be6c9a2b62d&oe=5EEAED11",
            "username": "san_jimz"
        },
        "likes_count": 2,
        "answers": []
    },
    {
        "id": 17847531317090380,
        "created_at": 1589389867,
        "text": "@rich24tkd \ud83d\udc4d",
        "owner": {
            "id": "2094271167",
            "is_verified": false,
            "profile_pic_url": "https://scontent-zrh1-1.cdninstagram.com/v/t51.2885-19/s150x150/13597718_270921506600365_1529898177_a.jpg?_nc_ht=scontent-zrh1-1.cdninstagram.com&_nc_ohc=e8RyhvSKqp4AX8FJGAk&oh=f31e6aa8609f88e2229f6cf85f83df88&oe=5EE9C5F6",
            "username": "evieschelseadad"
        },
        "likes_count": 2,
        "answers": [
            {
                "id": 18054307039237766,
                "created_at": 1589397585,
                "text": "@evieschelseadad bling! \ud83d\ude02",
                "owner": {
                    "id": "6843320108",
                    "is_verified": false,
                    "profile_pic_url": "https://scontent-zrh1-1.cdninstagram.com/v/t51.2885-19/s150x150/87885070_499951857576042_4984424695081205760_n.jpg?_nc_ht=scontent-zrh1-1.cdninstagram.com&_nc_ohc=oUeep78FQ9IAX_m0iIb&oh=e85333349e977ff00844ec942bf45e9a&oe=5EEADE70",
                    "username": "rich24tkd"
                },
                "likes_count": 1
            }
        ]
    },
    {
        "id": 17895430051489734,
        "created_at": 1589389047,
        "text": "@anacarlarn",
        "owner": {
            "id": "1497759738",
            "is_verified": false,
            "profile_pic_url": "https://scontent-zrh1-1.cdninstagram.com/v/t51.2885-19/s150x150/51243474_309984616372564_8150925373127786496_n.jpg?_nc_ht=scontent-zrh1-1.cdninstagram.com&_nc_ohc=1LrrrdzNswsAX8XM62N&oh=7bb1fe438cfa141b495506e0ec91b6bf&oe=5EEB1CC1",
            "username": "leonelpitta"
        },
        "likes_count": 2,
        "answers": [
            {
                "id": 17846882768116268,
                "created_at": 1589414483,
                "text": "@leonelpitta achei \ud83d\udc95",
                "owner": {
                    "id": "24789160",
                    "is_verified": false,
                    "profile_pic_url": "https://scontent-zrh1-1.cdninstagram.com/v/t51.2885-19/s150x150/83060282_208444940205967_576661907096731648_n.jpg?_nc_ht=scontent-zrh1-1.cdninstagram.com&_nc_ohc=TCl4WAPqR6oAX_D-euU&oh=b4a1d369d31718c12a9035b319316729&oe=5EE884C4",
                    "username": "anacarlarn"
                },
                "likes_count": 1
            },
            {
                "id": 17876462317648259,
                "created_at": 1589414362,
                "text": "@anacarlarn sim. Lindo, n\u00e3o achou?",
                "owner": {
                    "id": "1497759738",
                    "is_verified": false,
                    "profile_pic_url": "https://scontent-zrh1-1.cdninstagram.com/v/t51.2885-19/s150x150/51243474_309984616372564_8150925373127786496_n.jpg?_nc_ht=scontent-zrh1-1.cdninstagram.com&_nc_ohc=1LrrrdzNswsAX8XM62N&oh=7bb1fe438cfa141b495506e0ec91b6bf&oe=5EEB1CC1",
                    "username": "leonelpitta"
                },
                "likes_count": 1
            },
            {
                "id": 18150280252051682,
                "created_at": 1589389856,
                "text": "@leonelpitta ferminino ?",
                "owner": {
                    "id": "24789160",
                    "is_verified": false,
                    "profile_pic_url": "https://scontent-zrh1-1.cdninstagram.com/v/t51.2885-19/s150x150/83060282_208444940205967_576661907096731648_n.jpg?_nc_ht=scontent-zrh1-1.cdninstagram.com&_nc_ohc=TCl4WAPqR6oAX_D-euU&oh=b4a1d369d31718c12a9035b319316729&oe=5EE884C4",
                    "username": "anacarlarn"
                },
                "likes_count": 1
            }
        ]
    },
    {
        "id": 17875030423666257,
        "created_at": 1589388720,
        "text": "\u2764\ufe0f\ud83d\udc4c",
        "owner": {
            "id": "1978483282",
            "is_verified": false,
            "profile_pic_url": "https://scontent-zrh1-1.cdninstagram.com/v/t51.2885-19/s150x150/95662960_2868824479854062_456380695137222656_n.jpg?_nc_ht=scontent-zrh1-1.cdninstagram.com&_nc_ohc=kfuS22XbzCUAX-Rk2ap&oh=a5751756a2f96bda8fcac7ae31870d9e&oe=5EE85257",
            "username": "vicky_the_gym_22"
        },
        "likes_count": 0,
        "answers": []
    },
    {
        "id": 17861321551891969,
        "created_at": 1589386911,
        "text": "Nice \ud83c\udfc6\ud83d\udc4d\ud83d\ude0e",
        "owner": {
            "id": "10722404341",
            "is_verified": false,
            "profile_pic_url": "https://scontent-zrh1-1.cdninstagram.com/v/t51.2885-19/s150x150/68750489_2921451087881784_160570616536104960_n.jpg?_nc_ht=scontent-zrh1-1.cdninstagram.com&_nc_ohc=EW8h3wM2t-QAX9Zh6gD&oh=9c8d61690f1512c21ca7307b0ec96ebd&oe=5EEADEBE",
            "username": "radek3665"
        },
        "likes_count": 0,
        "answers": []
    },
    {
        "id": 17876704684630270,
        "created_at": 1589386452,
        "text": "@raanym_sh \ud83d\ude36\ud83d\ude36\ud83d\ude36\ud83d\ude36",
        "owner": {
            "id": "2083248212",
            "is_verified": false,
            "profile_pic_url": "https://scontent-zrh1-1.cdninstagram.com/v/t51.2885-19/s150x150/67440954_933835543644761_4755315351212785664_n.jpg?_nc_ht=scontent-zrh1-1.cdninstagram.com&_nc_ohc=nHgdXvnvwnwAX-kMIuO&oh=0e0220a60f675c67745685047435088b&oe=5EE832A4",
            "username": "nsiroussema"
        },
        "likes_count": 2,
        "answers": [
            {
                "id": 17952193984331302,
                "created_at": 1589386676,
                "text": "@nsiroussema \ud83d\ude2d\ud83d\ude2d\ud83d\ude2d\ud83d\ude2d\ud83d\udc94",
                "owner": {
                    "id": "7623724088",
                    "is_verified": false,
                    "profile_pic_url": "https://scontent-zrh1-1.cdninstagram.com/v/t51.2885-19/s150x150/92290872_307526963569889_5409431689208266752_n.jpg?_nc_ht=scontent-zrh1-1.cdninstagram.com&_nc_ohc=rafSl2OcVaAAX8vajY9&oh=87e3f0ae666a0c203c8fc5ebd5246cc8&oe=5EE982A8",
                    "username": "raanym_sh"
                },
                "likes_count": 1
            }
        ]
    },
    {
        "id": 17878893511616038,
        "created_at": 1589385817,
        "text": "Beautiful \u2764\ufe0f",
        "owner": {
            "id": "35357827214",
            "is_verified": false,
            "profile_pic_url": "https://scontent-zrh1-1.cdninstagram.com/v/t51.2885-19/s150x150/97209333_3059578587463451_9099150179516284928_n.jpg?_nc_ht=scontent-zrh1-1.cdninstagram.com&_nc_ohc=j5kYs6TGzHwAX-72loC&oh=0fe3d9bb666562af34033dd45fcba382&oe=5EEA477D",
            "username": "watches4everr"
        },
        "likes_count": 1,
        "answers": []
    },
    {
        "id": 17854182521002172,
        "created_at": 1589385496,
        "text": "Iiiiii Love \u00d4mega \u2764\ufe0f",
        "owner": {
            "id": "8485351378",
            "is_verified": false,
            "profile_pic_url": "https://scontent-zrh1-1.cdninstagram.com/v/t51.2885-19/s150x150/58410152_374233606508458_3556263213492338688_n.jpg?_nc_ht=scontent-zrh1-1.cdninstagram.com&_nc_ohc=nyelpKCLCZ0AX-NUX6i&oh=d88c1b56ede3d94581a452d18eb0bc28&oe=5EE8ECE1",
            "username": "dms_silva07"
        },
        "likes_count": 1,
        "answers": []
    },
    {
        "id": 17942619088354936,
        "created_at": 1589385387,
        "text": "\ud83d\udcaf\ud83d\udcaf\ud83d\udcaf",
        "owner": {
            "id": "935309312",
            "is_verified": false,
            "profile_pic_url": "https://scontent-zrh1-1.cdninstagram.com/v/t51.2885-19/10387920_1428671707405281_1083123716_a.jpg?_nc_ht=scontent-zrh1-1.cdninstagram.com&_nc_ohc=Mi6EBNaYtJcAX8AE6-s&oh=bb58cdd5f66973731879f1a7f3101f96&oe=5EEB208A",
            "username": "watchonisto"
        },
        "likes_count": 1,
        "answers": []
    },
    {
        "id": 17910108547439318,
        "created_at": 1589384711,
        "text": "Wishing you continued success & peace \ud83c\udf89\u2b50\ufe0f",
        "owner": {
            "id": "6041611407",
            "is_verified": false,
            "profile_pic_url": "https://scontent-zrh1-1.cdninstagram.com/v/t51.2885-19/s150x150/81455630_198671994605111_6974954509915127808_n.jpg?_nc_ht=scontent-zrh1-1.cdninstagram.com&_nc_ohc=lQ5ncYz_kTgAX_Ls9MH&oh=163c276567d66a095f496f062bd4d24f&oe=5EE7782A",
            "username": "realjohnglen"
        },
        "likes_count": 4,
        "answers": []
    },
    {
        "id": 17857124605922157,
        "created_at": 1589384145,
        "text": "Wonderful \ud83d\ude0d",
        "owner": {
            "id": "2313058781",
            "is_verified": false,
            "profile_pic_url": "https://scontent-zrh1-1.cdninstagram.com/v/t51.2885-19/s150x150/95320599_249324546218609_2994959396481531904_n.jpg?_nc_ht=scontent-zrh1-1.cdninstagram.com&_nc_ohc=aokESLIs7xEAX8K6O6n&oh=e258466759ae79eef271e6c54fa73f8d&oe=5EEAF5EA",
            "username": "hosainofficial.7"
        },
        "likes_count": 3,
        "answers": []
    },
    {
        "id": 18053373397239088,
        "created_at": 1589383939,
        "text": "It matches the diamonds on the soles of her hiking boots.",
        "owner": {
            "id": "17403927",
            "is_verified": false,
            "profile_pic_url": "https://scontent-zrh1-1.cdninstagram.com/v/t51.2885-19/s150x150/76997702_965844477106766_8866862611388432384_n.jpg?_nc_ht=scontent-zrh1-1.cdninstagram.com&_nc_ohc=n0wflRBNJqEAX8W9zcn&oh=6ec9f58083dc42e91d3d45389a087ebd&oe=5EEAC28E",
            "username": "allenmichaelmusic"
        },
        "likes_count": 1,
        "answers": []
    },
    {
        "id": 17850540806059414,
        "created_at": 1589383857,
        "text": "\ud83d\udc9b\ud83d\udc9b\ud83d\udc9b\ud83d\udc9b\ud83d\udc9b\ud83d\udc9b\ud83d\udc9b",
        "owner": {
            "id": "3090675895",
            "is_verified": false,
            "profile_pic_url": "https://scontent-zrh1-1.cdninstagram.com/v/t51.2885-19/s150x150/60225785_2208425786136232_5340380804205772800_n.jpg?_nc_ht=scontent-zrh1-1.cdninstagram.com&_nc_ohc=agr9wkTV1lwAX8ADckD&oh=143a77f982dbcaa4b218395739a865c1&oe=5EE92444",
            "username": "angel_shiny_oscar"
        },
        "likes_count": 4,
        "answers": []
    },
    {
        "id": 17842482575180289,
        "created_at": 1589383100,
        "text": "\ud83d\udc9b\ud83d\udc9b\ud83d\udc9b\ud83d\udc9b",
        "owner": {
            "id": "11340695905",
            "is_verified": false,
            "profile_pic_url": "https://scontent-zrh1-1.cdninstagram.com/v/t51.2885-19/s150x150/90233479_231101188070992_1545809814171418624_n.jpg?_nc_ht=scontent-zrh1-1.cdninstagram.com&_nc_ohc=q7bSsKXhvgoAX9a_LzX&oh=f074fc2a5111093be780a13003ef9c37&oe=5EE98A92",
            "username": "omegaladiesclub"
        },
        "likes_count": 4,
        "answers": []
    },
    {
        "id": 17880043885612768,
        "created_at": 1589383053,
        "text": "\ud83d\udc95\ud83d\udc95\ud83d\udc95\ud83d\udc95",
        "owner": {
            "id": "21561334153",
            "is_verified": false,
            "profile_pic_url": "https://scontent-zrh1-1.cdninstagram.com/v/t51.2885-19/s150x150/71560250_466863907372258_7011394064721379328_n.jpg?_nc_ht=scontent-zrh1-1.cdninstagram.com&_nc_ohc=qG_dKO2GqvcAX_zggtO&oh=fde629435f342631687b89707acf6f76&oe=5EE81B3D",
            "username": "olivegreendiets"
        },
        "likes_count": 1,
        "answers": []
    },
    {
        "id": 17860890685874050,
        "created_at": 1589382960,
        "text": "Like si tienes un Casio",
        "owner": {
            "id": "3042929928",
            "is_verified": false,
            "profile_pic_url": "https://scontent-zrh1-1.cdninstagram.com/v/t51.2885-19/s150x150/82551484_551607302098716_2021903262441013248_n.jpg?_nc_ht=scontent-zrh1-1.cdninstagram.com&_nc_ohc=9h-7JQhMZVYAX_aJxD7&oh=78956139e2a892f248a00aebd8ba950e&oe=5EEAF0A7",
            "username": "diegoibarra__"
        },
        "likes_count": 4,
        "answers": [
            {
                "id": 17857188892908935,
                "created_at": 1589402586,
                "text": "@ffuentesp que cool, con que correa lo tienes?",
                "owner": {
                    "id": "3042929928",
                    "is_verified": false,
                    "profile_pic_url": "https://scontent-zrh1-1.cdninstagram.com/v/t51.2885-19/s150x150/82551484_551607302098716_2021903262441013248_n.jpg?_nc_ht=scontent-zrh1-1.cdninstagram.com&_nc_ohc=9h-7JQhMZVYAX_aJxD7&oh=78956139e2a892f248a00aebd8ba950e&oe=5EEAF0A7",
                    "username": "diegoibarra__"
                },
                "likes_count": 0
            },
            {
                "id": 18141779344053007,
                "created_at": 1589401706,
                "text": "@diegoibarra__ justo ando con mi GMW-B5000 jeje",
                "owner": {
                    "id": "23728367",
                    "is_verified": false,
                    "profile_pic_url": "https://scontent-zrh1-1.cdninstagram.com/v/t51.2885-19/s150x150/17076923_264858037285055_428423370028089344_a.jpg?_nc_ht=scontent-zrh1-1.cdninstagram.com&_nc_ohc=o8npeWOI4nUAX-fjNhz&oh=ab6f027f26f2e2804a69b777af2b393b&oe=5EE8A636",
                    "username": "ffuentesp"
                },
                "likes_count": 1
            }
        ]
    },
    {
        "id": 18110602216126367,
        "created_at": 1589382888,
        "text": "\ud83d\ude0d\ud83d\ude0d\ud83d\ude0d\ud83d\ude0d\ud83d\ude0d\ud83d\ude0d\ud83d\ude0d\ud83d\ude0d\ud83d\ude0d\ud83d\ude0d\ud83d\ude0d\ud83d\ude0d\ud83d\ude0d",
        "owner": {
            "id": "8235091964",
            "is_verified": false,
            "profile_pic_url": "https://scontent-zrh1-1.cdninstagram.com/v/t51.2885-19/s150x150/70335188_2532064647030161_8879814750989451264_n.jpg?_nc_ht=scontent-zrh1-1.cdninstagram.com&_nc_ohc=AMCTIddMeXwAX8VcfCS&oh=a5b187444acd9dc587eae4d3ba3808ca&oe=5EE8D018",
            "username": "royal_paint_pro_swirl_removal"
        },
        "likes_count": 5,
        "answers": []
    },
    {
        "id": 17902366450464569,
        "created_at": 1589382874,
        "text": "Stunning",
        "owner": {
            "id": "8729059926",
            "is_verified": false,
            "profile_pic_url": "https://scontent-zrh1-1.cdninstagram.com/v/t51.2885-19/s150x150/43025532_331081384291208_4851438501708693504_n.jpg?_nc_ht=scontent-zrh1-1.cdninstagram.com&_nc_ohc=EeGcNJpeMqcAX8xgJMu&oh=d71e66e0d3845ab9fbf0ecd994eed479&oe=5EE7FB4A",
            "username": "ng.roger.520"
        },
        "likes_count": 5,
        "answers": []
    },
    {
        "id": 17911025425427913,
        "created_at": 1589382661,
        "text": "\ud83d\udc4d",
        "owner": {
            "id": "12127016159",
            "is_verified": false,
            "profile_pic_url": "https://scontent-zrh1-1.cdninstagram.com/v/t51.2885-19/s150x150/89828687_593388327917617_5718617137782718464_n.jpg?_nc_ht=scontent-zrh1-1.cdninstagram.com&_nc_ohc=hhzN3n3CnO8AX9igvq4&oh=6c868c43063a13be52ef8d3ecddfc2d3&oe=5EEA754D",
            "username": "p.multicolore"
        },
        "likes_count": 5,
        "answers": []
    },
    {
        "id": 17882460934589996,
        "created_at": 1589382528,
        "text": "Me likey",
        "owner": {
            "id": "5995596122",
            "is_verified": false,
            "profile_pic_url": "https://scontent-zrh1-1.cdninstagram.com/v/t51.2885-19/s150x150/64763414_333461930658510_5474310348490145792_n.jpg?_nc_ht=scontent-zrh1-1.cdninstagram.com&_nc_ohc=a41Dzq_gp1gAX-A7pp3&oh=cccc241002a46ac5773bdc712d101027&oe=5EE7D477",
            "username": "pauljsr_"
        },
        "likes_count": 3,
        "answers": []
    },
    {
        "id": 18097887808157205,
        "created_at": 1589382155,
        "text": "Stunning!",
        "owner": {
            "id": "9754357333",
            "is_verified": false,
            "profile_pic_url": "https://scontent-zrh1-1.cdninstagram.com/v/t51.2885-19/s150x150/61990981_473469706747062_2680591365489819648_n.jpg?_nc_ht=scontent-zrh1-1.cdninstagram.com&_nc_ohc=54MXvRPSQfUAX9fAVZA&oh=943c0a8211eea82033dd5c1b6626d442&oe=5EE8CD2D",
            "username": "silverwoodstudiosuk"
        },
        "likes_count": 2,
        "answers": []
    },
    {
        "id": 17851434155055457,
        "created_at": 1589382146,
        "text": "Stunning",
        "owner": {
            "id": "9754357333",
            "is_verified": false,
            "profile_pic_url": "https://scontent-zrh1-1.cdninstagram.com/v/t51.2885-19/s150x150/61990981_473469706747062_2680591365489819648_n.jpg?_nc_ht=scontent-zrh1-1.cdninstagram.com&_nc_ohc=54MXvRPSQfUAX9fAVZA&oh=943c0a8211eea82033dd5c1b6626d442&oe=5EE8CD2D",
            "username": "silverwoodstudiosuk"
        },
        "likes_count": 3,
        "answers": []
    },
    {
        "id": 17853358934018862,
        "created_at": 1589382120,
        "text": "\ud83d\udc9b",
        "owner": {
            "id": "4525041377",
            "is_verified": false,
            "profile_pic_url": "https://scontent-zrh1-1.cdninstagram.com/v/t51.2885-19/s150x150/83524201_2508392119410168_4695182128281812992_n.jpg?_nc_ht=scontent-zrh1-1.cdninstagram.com&_nc_ohc=sUnY-40Uw5UAX-j3SDT&oh=f8b92a46ef9afc6db2adc89377140ad4&oe=5EE804F5",
            "username": "karina_boheme"
        },
        "likes_count": 1,
        "answers": []
    },
    {
        "id": 17872991476701260,
        "created_at": 1589382067,
        "text": "\ud83d\udd25\ud83d\udd25\ud83d\ude0d",
        "owner": {
            "id": "753260819",
            "is_verified": false,
            "profile_pic_url": "https://scontent-zrh1-1.cdninstagram.com/v/t51.2885-19/s150x150/96141087_2924338054270235_6563137424778592256_n.jpg?_nc_ht=scontent-zrh1-1.cdninstagram.com&_nc_ohc=kUhaHcfHDasAX-D7R4g&oh=c584523ee0aead1974998c8be3270f37&oe=5EEAE2D0",
            "username": "guillaume.oliveira"
        },
        "likes_count": 3,
        "answers": []
    }
]